fast_lsh_ann/__init__.py
fast_lsh_ann/__pycache__/__init__.cpython-310.pyc
fast_lsh_ann/__pycache__/__init__.cpython-312.pyc
fast_lsh_ann/__pycache__/__init__.cpython-313.pyc
fast_lsh_ann/__pycache__/delta_utils.cpython-313.pyc
fast_lsh_ann/__pycache__/streaming.cpython-313.pyc
fast_lsh_ann/_fast_lsh_ann.cpython-313-darwin.so
fast_lsh_ann/_fast_lsh_ann.pyi
fast_lsh_ann/delta_utils.py
fast_lsh_ann/streaming.py
fast_lsh_ann-0.1.1.dist-info/METADATA
fast_lsh_ann-0.1.1.dist-info/WHEEL
fast_lsh_ann-0.1.1.dist-info/RECORD
