Metadata-Version: 2.4
Name: fast_lsh_ann
Version: 0.1.1
Classifier: Programming Language :: Rust
Classifier: Programming Language :: Python :: Implementation :: CPython
Classifier: Programming Language :: Python :: 3
Classifier: Programming Language :: Python :: 3.9
Classifier: Programming Language :: Python :: 3.10
Classifier: Programming Language :: Python :: 3.11
Classifier: Programming Language :: Python :: 3.12
Classifier: Programming Language :: Python :: 3.13
Classifier: Development Status :: 4 - Beta
Classifier: Intended Audience :: Developers
Classifier: Intended Audience :: Science/Research
Classifier: Topic :: Scientific/Engineering :: Artificial Intelligence
Requires-Dist: numpy>=1.20
Requires-Dist: faiss-cpu>=1.7 ; extra == 'benchmark'
Requires-Dist: pytest>=7.0 ; extra == 'dev'
Requires-Dist: maturin>=1.4 ; extra == 'dev'
Provides-Extra: benchmark
Provides-Extra: dev
Summary: Fast Bucketed Random Projection LSH for Approximate Nearest Neighbor search
Keywords: lsh,ann,nearest-neighbor,similarity-search,vector-search
License: MIT
Requires-Python: >=3.9
